former/__init__.py
former/cli.py
former/resource.py
former/specification.py
former-0.2.7.dist-info/LICENSE
former-0.2.7.dist-info/METADATA
former-0.2.7.dist-info/WHEEL
former-0.2.7.dist-info/entry_points.txt
former-0.2.7.dist-info/top_level.txt
former-0.2.7.dist-info/RECORD
